math_problem_generator/__init__.py
math_problem_generator/generator.py
math_problem_generator-0.0.3.dist-info/LICENSE
math_problem_generator-0.0.3.dist-info/METADATA
math_problem_generator-0.0.3.dist-info/WHEEL
math_problem_generator-0.0.3.dist-info/top_level.txt
math_problem_generator-0.0.3.dist-info/RECORD
