Metadata-Version: 2.1
Name: math-problem-generator
Version: 0.0.3
Summary: A package for generating math problems
Home-page: https://github.com/tobiasbp/math-problem-generator
Author: Tobias Balle-Petersen
Author-email: tobiasbp@gmail.com
License: UNKNOWN
Project-URL: Bug Tracker, https://github.com/tobiasbp/math-problem-generator/issues
Platform: UNKNOWN
Classifier: Programming Language :: Python :: 3
Classifier: License :: OSI Approved :: GNU Affero General Public License v3
Classifier: Operating System :: OS Independent
Requires-Python: >=3.8
License-File: LICENSE
